epub_reader/__init__.py
epub_reader/main.py
epub_reader-1.0.2.dist-info/LICENSE
epub_reader-1.0.2.dist-info/METADATA
epub_reader-1.0.2.dist-info/WHEEL
epub_reader-1.0.2.dist-info/entry_points.txt
epub_reader-1.0.2.dist-info/top_level.txt
epub_reader-1.0.2.dist-info/RECORD
