Metadata-Version: 2.1
Name: epub-reader
Version: 1.0.2
Summary: Python CLI Epub reader with page navigation, bookmarks management, search management, save pages and book to text files and reading sessions to save and load your current progress 
Home-page: https://github.com/fairy-root/epub_reader
Author: fairy-root
Author-email: fairyvmos@gmail.com
Classifier: Programming Language :: Python :: 3
Classifier: License :: OSI Approved :: MIT License
Classifier: Operating System :: OS Independent
Requires-Python: >=3.6
License-File: LICENSE
Requires-Dist: beautifulsoup4
